function.py
mcp_server.py
iflow_mcp_simonutd_ai_diagram_prototype_generator_mcp_server-0.1.0.dist-info/licenses/LICENSE
prompts/drawIO_architecture_prompt.md
prompts/drawIO_empathyMap_prompt.md
prompts/drawIO_flowChart_prompt.md
prompts/drawIO_prototype_prompt.md
prompts/drawIO_pyramidDiagram_prompt.md
prompts/drawIO_serviceBlueprint_prompt.md
prompts/drawIO_userJourneyMap_prompt.md
prompts/drawIO_userPersona_prompt.md
prompts/drawIO_userStoryMap_prompt.md
prompts/html_Interactive3D_prompt.md
prompts/html_apple_mobile_prototype_prompt.md
prompts/html_common_prototype_prompt.md
prompts/html_meetingSummary_prompt.md
prompts/html_prototype_prompt.md
prompts/html_studyby3D_prompt.md
prompts/html_userPersona_prompt.md
prompts/html_weChatMiniApp_prompt.md
prompts/json_ppt_plan_prompt.md
prompts/svg_feynmanInfoGraphics_prompt.md
prompts/svg_posterDesigner_prompt.md
prompts/svg_ppt_svg_prompt.md
prompts/svg_pyramidDiagram_prompt.md
standardFileTemplate/drawio.md
standardFileTemplate/mobile_html.md
standardFileTemplate/svg.md
standardFileTemplate/web_html.md
iflow_mcp_simonutd_ai_diagram_prototype_generator_mcp_server-0.1.0.dist-info/METADATA
iflow_mcp_simonutd_ai_diagram_prototype_generator_mcp_server-0.1.0.dist-info/WHEEL
iflow_mcp_simonutd_ai_diagram_prototype_generator_mcp_server-0.1.0.dist-info/entry_points.txt
iflow_mcp_simonutd_ai_diagram_prototype_generator_mcp_server-0.1.0.dist-info/top_level.txt
iflow_mcp_simonutd_ai_diagram_prototype_generator_mcp_server-0.1.0.dist-info/RECORD
