Metadata-Version: 2.4
Name: iflow-mcp_simonutd_ai-diagram-prototype-generator-mcp-server
Version: 0.1.0
Summary: Add your description here
Requires-Python: >=3.10
License-File: LICENSE
Requires-Dist: python-dotenv>=1.0.0
Requires-Dist: mcp>=1.12.4
Requires-Dist: openai>=1.99.9
Requires-Dist: zhipuai>=2.1.5.20250801
Dynamic: license-file
